CHANGES.txt
CONTRIBUTORS.txt
README.txt
TODO.txt
bootstrap.py
buildout.cfg
setup.py
z3c/__init__.py
z3c.recipe.eggbasket.egg-info/PKG-INFO
z3c.recipe.eggbasket.egg-info/SOURCES.txt
z3c.recipe.eggbasket.egg-info/dependency_links.txt
z3c.recipe.eggbasket.egg-info/entry_points.txt
z3c.recipe.eggbasket.egg-info/namespace_packages.txt
z3c.recipe.eggbasket.egg-info/not-zip-safe
z3c.recipe.eggbasket.egg-info/requires.txt
z3c.recipe.eggbasket.egg-info/top_level.txt
z3c/recipe/__init__.py
z3c/recipe/eggbasket/README.txt
z3c/recipe/eggbasket/__init__.py
z3c/recipe/eggbasket/creator.py
z3c/recipe/eggbasket/downloader.py
z3c/recipe/eggbasket/utils.py
z3c/recipe/eggbasket/tests/__init__.py
z3c/recipe/eggbasket/tests/test_docs.py
z3c/recipe/eggbasket/tests/colour/README.txt
z3c/recipe/eggbasket/tests/colour/setup.py
z3c/recipe/eggbasket/tests/colour/colour/__init__.py
z3c/recipe/eggbasket/tests/orange/README.txt
z3c/recipe/eggbasket/tests/orange/setup.py
z3c/recipe/eggbasket/tests/orange/orange/__init__.py
