Metadata-Version: 1.0
Name: z3c.recipe.eggbasket
Version: 0.4.0
Summary: Install eggs from a tarball and create that egg.
Home-page: https://launchpad.net/grok
Author: Grok Team
Author-email: grok-dev@zope.org
License: ZPL
Platform: UNKNOWN
Classifier: Framework :: Buildout
Classifier: Intended Audience :: Developers
Classifier: Topic :: Software Development :: Build Tools
Classifier: Topic :: Software Development :: Libraries :: Python Modules
Classifier: License :: OSI Approved :: Zope Public License
